bitpay/__init__.py
bitpay/bitpay_setup.py
bitpay/client.py
bitpay/config.py
bitpay/environment.py
bitpay/clients/__init__.py
bitpay/clients/bill_client.py
bitpay/clients/bitpay_client.py
bitpay/clients/currency_client.py
bitpay/clients/invoice_client.py
bitpay/clients/ledger_client.py
bitpay/clients/payout_client.py
bitpay/clients/payout_recipient_client.py
bitpay/clients/rate_client.py
bitpay/clients/refund_client.py
bitpay/clients/response_parser.py
bitpay/clients/settlement_client.py
bitpay/clients/wallet_client.py
bitpay/exceptions/__init__.py
bitpay/exceptions/bitpay_api_exception.py
bitpay/exceptions/bitpay_exception.py
bitpay/exceptions/bitpay_exception_provider.py
bitpay/exceptions/bitpay_generic_exception.py
bitpay/exceptions/bitpay_validation_exception.py
bitpay/logger/__init__.py
bitpay/logger/bitpay_logger.py
bitpay/logger/logger_provider.py
bitpay/logger/logging_logger.py
bitpay/models/__init__.py
bitpay/models/bitpay_model.py
bitpay/models/currency.py
bitpay/models/facade.py
bitpay/models/bill/__init__.py
bitpay/models/bill/bill.py
bitpay/models/bill/bill_status.py
bitpay/models/bill/item.py
bitpay/models/invoice/__init__.py
bitpay/models/invoice/buyer.py
bitpay/models/invoice/buyer_fields.py
bitpay/models/invoice/buyer_provided_info.py
bitpay/models/invoice/invoice.py
bitpay/models/invoice/invoice_event_token.py
bitpay/models/invoice/invoice_refund_addresses.py
bitpay/models/invoice/invoice_status.py
bitpay/models/invoice/invoice_webhook.py
bitpay/models/invoice/itemized_details.py
bitpay/models/invoice/miner_fees.py
bitpay/models/invoice/miner_fees_item.py
bitpay/models/invoice/refund.py
bitpay/models/invoice/refund_info.py
bitpay/models/invoice/refund_status.py
bitpay/models/invoice/refund_webhook.py
bitpay/models/invoice/shopper.py
bitpay/models/invoice/supported_transaction_currencies.py
bitpay/models/invoice/supported_transaction_currency.py
bitpay/models/invoice/transaction.py
bitpay/models/invoice/universal_codes.py
bitpay-7.0.8.dist-info/licenses/LICENSE
bitpay-7.0.8.dist-info/METADATA
bitpay-7.0.8.dist-info/WHEEL
bitpay-7.0.8.dist-info/top_level.txt
bitpay-7.0.8.dist-info/RECORD
