Metadata-Version: 2.4
Name: bitpay
Version: 7.0.8
Summary: Accept bitcoin with BitPay
Author-email: Antonio Buedo <sales-engineering@bitpay.com>
Project-URL: Homepage, https://github.com/bitpay/python-bitpay-client
Project-URL: Bug Tracker, https://github.com/bitpay/python-bitpay-client/issues
Keywords: bitcoin,payments,crypto,cash,ethereum,online payments
Classifier: Programming Language :: Python :: 3.9
Classifier: Programming Language :: Python :: 3.10
Classifier: Programming Language :: Python :: 3.11
Classifier: Programming Language :: Python :: 3.12
Classifier: Programming Language :: Python :: 3.13
Classifier: Programming Language :: Python :: 3.14
Classifier: Development Status :: 5 - Production/Stable
Classifier: Environment :: Web Environment
Classifier: Intended Audience :: Developers
Classifier: License :: OSI Approved :: MIT License
Classifier: Natural Language :: English
Classifier: Operating System :: OS Independent
Classifier: Topic :: Office/Business :: Financial
Classifier: Topic :: Software Development :: Libraries :: Python Modules
Requires-Python: >=3.9
License-File: LICENSE
Requires-Dist: ecdsa>=0.19.1
Requires-Dist: requests>=2.32.5
Requires-Dist: pydantic==2.11.9
Provides-Extra: dev
Requires-Dist: black; extra == "dev"
Requires-Dist: pytest; extra == "dev"
Requires-Dist: pytest-mock; extra == "dev"
Requires-Dist: mypy; extra == "dev"
Requires-Dist: pytest-mypy-plugins; extra == "dev"
Requires-Dist: pytest-cov; extra == "dev"
Dynamic: license-file
